{
  "category": "Blocos autónomos tipo permanente",
  "rules": [
    {
      "id": "ELEC_R251",
      "reference": "Portaria 1532/2008, Art. 115 n.1",
      "category": "Instalações Elétricas",
      "subcategory": "Blocos autónomos tipo permanente",
      "rule_text": "UT IV-VI, VIII, X, XI (exceto dormida): blocos autónomos obrigatoriamente do tipo permanente",
      "parameters": {
        "uts_permanente": [
          "IV",
          "V",
          "VI",
          "VIII",
          "X",
          "XI"
        ],
        "excecao": "espaços dormida risco D e E"
      },
      "validation_type": "formula",
      "severity": "mandatory",
      "formula": "if ut in ['IV','V','VI','VIII','X','XI'] and not espaco_dormida: bloco_tipo == 'permanente'",
      "lookup_tables": {
        "uts_permanente": [
          "IV",
          "V",
          "VI",
          "VIII",
          "X",
          "XI"
        ],
        "excecao": "espaços dormida risco D e E"
      },
      "error_message": "Bloco autónomo deve ser do tipo permanente nesta utilização-tipo",
      "success_message": "✓ Conforme: Blocos autónomos tipo permanente",
      "source": {
        "regulation": "Portaria 1532/2008",
        "article": "Portaria 1532/2008, Art. 115 n.1",
        "version": "3.0",
        "date": "2026-02-15"
      },
      "metadata": {
        "complexity": "complex",
        "requires_calculation": true,
        "application_scope": [
          "Geral"
        ]
      }
    }
  ]
}