{
  "category": "Dimensões ductos",
  "rules": [
    {
      "id": "ELEC_R054",
      "reference": "RTIEBT Quadro 803B",
      "category": "Instalações Elétricas",
      "subcategory": "Dimensões ductos",
      "rule_text": "Dimensões mínimas dos ductos de colunas",
      "parameters": {
        "lookup_table": {
          "In<=200A": {
            "profundidade_cm": 30,
            "L1_cm": 60,
            "porta_cm": 63
          },
          "200A<In<=400A": {
            "profundidade_cm": 30,
            "L1_cm": 103,
            "porta_cm": 103
          },
          "In>400A": {
            "profundidade_cm": 30,
            "L1_cm": 130,
            "porta_cm": 130
          }
        }
      },
      "validation_type": "formula",
      "severity": "mandatory",
      "formula": "duct_dims >= lookup_803B(In_category)",
      "lookup_tables": {
        "lookup_table": {
          "In<=200A": {
            "profundidade_cm": 30,
            "L1_cm": 60,
            "porta_cm": 63
          },
          "200A<In<=400A": {
            "profundidade_cm": 30,
            "L1_cm": 103,
            "porta_cm": 103
          },
          "In>400A": {
            "profundidade_cm": 30,
            "L1_cm": 130,
            "porta_cm": 130
          }
        }
      },
      "error_message": "Dimensões do ducto inferiores ao mínimo (Quadro 803B)",
      "success_message": "✓ Conforme: Dimensões ductos",
      "source": {
        "regulation": "RTIEBT",
        "article": "RTIEBT Quadro 803B",
        "version": "3.0",
        "date": "2026-02-15"
      },
      "metadata": {
        "complexity": "complex",
        "requires_calculation": true,
        "application_scope": [
          "Geral"
        ]
      }
    }
  ]
}