{
  "category": "Piscinas - TRS volumes 0 e 1",
  "rules": [
    {
      "id": "ELEC_R075",
      "reference": "RTIEBT Secção 702.471.0",
      "category": "Instalações Elétricas",
      "subcategory": "Piscinas - TRS volumes 0 e 1",
      "rule_text": "Volumes 0 e 1: apenas TRS ≤ 12V AC / 30V DC",
      "parameters": {
        "max_AC_V": 12,
        "max_DC_V": 30
      },
      "validation_type": "formula",
      "severity": "mandatory",
      "formula": "IF pool_Vol_0_or_1 THEN voltage<=TRS",
      "lookup_tables": null,
      "error_message": "Tensão nos volumes 0/1 da piscina excede TRS (702.471.0)",
      "success_message": "✓ Conforme: Piscinas - TRS volumes 0 e 1",
      "source": {
        "regulation": "RTIEBT",
        "article": "RTIEBT Secção 702.471.0",
        "version": "3.0",
        "date": "2026-02-15"
      },
      "metadata": {
        "complexity": "complex",
        "requires_calculation": true,
        "application_scope": [
          "Piscinas"
        ]
      }
    }
  ]
}